multiton/__init__.py
multiton/multiton.py
multiton-0.2.3.dist-info/DESCRIPTION.rst
multiton-0.2.3.dist-info/METADATA
multiton-0.2.3.dist-info/RECORD
multiton-0.2.3.dist-info/WHEEL
multiton-0.2.3.dist-info/metadata.json
multiton-0.2.3.dist-info/top_level.txt
