Metadata-Version: 2.0
Name: multiton
Version: 0.2.3
Summary: A Multiton metaclass for preventing duplicate instances based on init values.
Home-page: https://github.com/laundmo/multiton
Author: Laurin Schmidt
Author-email: laurinschmidt2001@gmail.com
License: MIT license
Keywords: multiton
Platform: UNKNOWN
Classifier: Development Status :: 2 - Pre-Alpha
Classifier: Intended Audience :: Developers
Classifier: License :: OSI Approved :: MIT License
Classifier: Natural Language :: English
Classifier: Programming Language :: Python :: 3
Classifier: Programming Language :: Python :: 3.6
Classifier: Programming Language :: Python :: 3.7
Classifier: Programming Language :: Python :: 3.8
Requires-Python: >=3.6
